pitchmark/__init__.py
pitchmark/course.py
pitchmark/geom.py
pitchmark/hole.py
pitchmark/lidar/__init__.py
pitchmark/lidar/las.py
pitchmark/osm/__init__.py
pitchmark/osm/osm.py
pitchmark/plotting.py
pitchmark-0.3.1.dist-info/LICENSE
pitchmark-0.3.1.dist-info/METADATA
pitchmark-0.3.1.dist-info/WHEEL
pitchmark-0.3.1.dist-info/RECORD
