Metadata-Version: 2.1
Name: pitchmark
Version: 0.3.1
Summary: Exploring golf shot strategy.
License: MIT
Author: Istvan Kleijn
Requires-Python: >=3.10,<4.0
Classifier: License :: OSI Approved :: MIT License
Classifier: Programming Language :: Python :: 3
Classifier: Programming Language :: Python :: 3.10
Classifier: Programming Language :: Python :: 3.11
Requires-Dist: altair (>=4.2.2,<5.0.0)
Requires-Dist: geopandas (>=0.12.2,<0.13.0)
Requires-Dist: laspy (>=2.4.1,<3.0.0)
Requires-Dist: laszip (>=0.2.2,<0.3.0)
Requires-Dist: numpy (>=1.24.2,<2.0.0)
Requires-Dist: open3d (==0.16.0)
Requires-Dist: osmium (>=3.6.0,<4.0.0)
Requires-Dist: pandas (>=1.5.3,<2.0.0)
Requires-Dist: pyproj (>=3.4.1,<4.0.0)
Requires-Dist: shapely (>=2.0.1,<3.0.0)
